cdktf_local_exec/__init__.py
cdktf_local_exec/py.typed
cdktf_local_exec/_jsii/__init__.py
cdktf_local_exec/_jsii/cdktf-local-exec@0.6.28.jsii.tgz
cdktf_local_exec-0.6.28.dist-info/LICENSE
cdktf_local_exec-0.6.28.dist-info/METADATA
cdktf_local_exec-0.6.28.dist-info/WHEEL
cdktf_local_exec-0.6.28.dist-info/top_level.txt
cdktf_local_exec-0.6.28.dist-info/RECORD
